orpyter/__init__.py
orpyter/_about.py
orpyter/_cli.py
orpyter/core.py
orpyter/export.py
orpyter/api/__init__.py
orpyter/api/fastapi_app.py
orpyter/api/fastapi_utils.py
orpyter/components/__init__.py
orpyter/components/outputs.py
orpyter/components/types.py
orpyter/tasks/__init__.py
orpyter/ui/__init__.py
orpyter/ui/schema_utils.py
orpyter/ui/streamlit_ui.py
orpyter/ui/streamlit_utils.py
orpyter/utils/__init__.py
orpyter-0.0.2.dist-info/LICENSE
orpyter-0.0.2.dist-info/METADATA
orpyter-0.0.2.dist-info/WHEEL
orpyter-0.0.2.dist-info/entry_points.txt
orpyter-0.0.2.dist-info/top_level.txt
orpyter-0.0.2.dist-info/RECORD
